voxgram/__init__.py
voxgram/client.py
voxgram/dispatcher.py
voxgram/emoji.py
voxgram/file_id.py
voxgram/filters.py
voxgram/mime_types.py
voxgram/py.typed
voxgram/sync.py
voxgram/utils.py
voxgram/connection/__init__.py
voxgram/connection/connection.py
voxgram/connection/transport/__init__.py
voxgram/connection/transport/tcp/__init__.py
voxgram/connection/transport/tcp/tcp.py
voxgram/connection/transport/tcp/tcp_abridged.py
voxgram/connection/transport/tcp/tcp_abridged_o.py
voxgram/connection/transport/tcp/tcp_full.py
voxgram/connection/transport/tcp/tcp_intermediate.py
voxgram/connection/transport/tcp/tcp_intermediate_o.py
voxgram/crypto/__init__.py
voxgram/crypto/aes.py
voxgram/crypto/mtproto.py
voxgram/crypto/prime.py
voxgram/crypto/rsa.py
voxgram/enums/__init__.py
voxgram/enums/auto_name.py
voxgram/enums/chat_action.py
voxgram/enums/chat_event_action.py
voxgram/enums/chat_member_status.py
voxgram/enums/chat_members_filter.py
voxgram/enums/chat_type.py
voxgram/enums/listerner_types.py
voxgram/enums/message_entity_type.py
voxgram/enums/message_media_type.py
voxgram/enums/message_service_type.py
voxgram/enums/messages_filter.py
voxgram/enums/next_code_type.py
voxgram/enums/parse_mode.py
voxgram/enums/poll_type.py
voxgram/enums/profile_color.py
voxgram/enums/reply_color.py
voxgram/enums/sent_code_type.py
voxgram/enums/stories_privacy_rules.py
voxgram/enums/story_privacy.py
voxgram/enums/user_status.py
voxgram/errors/__init__.py
voxgram/errors/rpc_error.py
voxgram/errors/pyromod/__init__.py
voxgram/errors/pyromod/listener_stopped.py
voxgram/errors/pyromod/listener_timeout.py
voxgram/handlers/__init__.py
voxgram/handlers/callback_query_handler.py
voxgram/handlers/chat_join_request_handler.py
voxgram/handlers/chat_member_updated_handler.py
voxgram/handlers/chosen_inline_result_handler.py
voxgram/handlers/conversation_handler.py
voxgram/handlers/deleted_messages_handler.py
voxgram/handlers/disconnect_handler.py
voxgram/handlers/edited_message_handler.py
voxgram-1.169.0.dist-info/METADATA
voxgram-1.169.0.dist-info/NOTICE
voxgram-1.169.0.dist-info/WHEEL
voxgram-1.169.0.dist-info/top_level.txt
voxgram-1.169.0.dist-info/RECORD
